srmbench/__init__.py
srmbench/__version__.py
srmbench/datasets/__init__.py
srmbench/datasets/even_pixels.py
srmbench/datasets/mnist_sudoku.py
srmbench/datasets/srm_dataset.py
srmbench/datasets/counting_objects/__init__.py
srmbench/datasets/counting_objects/counting_objects.py
srmbench/datasets/counting_objects/counting_objects_ffhq.py
srmbench/datasets/counting_objects/counting_objects_subdataset.py
srmbench/datasets/counting_objects/ffhq.py
srmbench/datasets/counting_objects/font_cache.py
srmbench/datasets/counting_objects/labelers.py
srmbench/evaluations/__init__.py
srmbench/evaluations/counting_objects_evaluation.py
srmbench/evaluations/even_pixels_evaluation.py
srmbench/evaluations/mnist_sudoku_evaluation.py
srmbench-1.0.3.dist-info/licenses/LICENSE
srmbench-1.0.3.dist-info/METADATA
srmbench-1.0.3.dist-info/WHEEL
srmbench-1.0.3.dist-info/entry_points.txt
srmbench-1.0.3.dist-info/top_level.txt
srmbench-1.0.3.dist-info/RECORD
