Metadata-Version: 2.4
Name: srmbench
Version: 1.0.3
Summary: Datasets and evaluation from the Spatial Reasoning with Denoising Models paper
Author-email: Bartlomiej Pogodzinski <bpogodzi@mpi-inf.mpg.de>, Christopher Wewer <cwewer@mpi-inf.mpg.de>, Jan Eric Lenssen <jan.lenssen@mpi-inf.mpg.de>
Maintainer-email: Bartlomiej Pogodzinski <bpogodzi@mpi-inf.mpg.de>
License: MIT
Project-URL: repository, https://github.com/spatialreasoners/srmbench
Project-URL: bug_tracker, https://github.com/spatialreasoners/srmbench/issues
Keywords: spatial reasoning,diffusion models,flow matching,image generation,benchmark
Classifier: Development Status :: 3 - Alpha
Classifier: Intended Audience :: Developers
Classifier: Intended Audience :: Science/Research
Classifier: License :: OSI Approved :: MIT License
Classifier: Operating System :: OS Independent
Classifier: Programming Language :: Python :: 3
Classifier: Programming Language :: Python :: 3.10
Classifier: Programming Language :: Python :: 3.11
Classifier: Programming Language :: Python :: 3.12
Classifier: Programming Language :: Python :: 3.13
Classifier: Programming Language :: Python :: 3.14
Classifier: Topic :: Scientific/Engineering :: Artificial Intelligence
Classifier: Topic :: Software Development :: Libraries :: Python Modules
Requires-Python: >=3.10
License-File: LICENSE
Requires-Dist: torch>=1.9.0
Requires-Dist: torchvision>=0.10.0
Requires-Dist: numpy>=1.21.0
Requires-Dist: pandas>=1.3.0
Requires-Dist: huggingface-hub>=0.16.0
Requires-Dist: safetensors>=0.3.0
Requires-Dist: jaxtyping>=0.2.0
Requires-Dist: beartype>=0.15.0
Provides-Extra: dev
Requires-Dist: pytest>=7.0.0; extra == "dev"
Requires-Dist: pytest-cov>=4.0.0; extra == "dev"
Requires-Dist: black>=22.0.0; extra == "dev"
Requires-Dist: isort>=5.10.0; extra == "dev"
Requires-Dist: flake8>=5.0.0; extra == "dev"
Requires-Dist: mypy>=1.0.0; extra == "dev"
Requires-Dist: pre-commit>=2.20.0; extra == "dev"
Provides-Extra: docs
Requires-Dist: sphinx>=5.0.0; extra == "docs"
Requires-Dist: sphinx-rtd-theme>=1.0.0; extra == "docs"
Requires-Dist: myst-parser>=0.18.0; extra == "docs"
Provides-Extra: all
Requires-Dist: srmbench[dev,docs]; extra == "all"
Dynamic: license-file
